chartbuilder/__init__.py
chartbuilder/admin.py
chartbuilder/api_urls.py
chartbuilder/api_views.py
chartbuilder/cms_plugins.py
chartbuilder/models.py
chartbuilder/urls.py
chartbuilder/migrations/0001_initial.py
chartbuilder/migrations/__init__.py
chartbuilder/static/.DS_Store
chartbuilder/static/chartbuilder/credits.txt
chartbuilder/static/chartbuilder/css/main.css
chartbuilder/static/chartbuilder/js/main.js
chartbuilder/templates/admin/chartbuilder/chart/change_form.html
chartbuilder/templates/chartbuilder/chartbuilder.html
chartbuilder/templates/chartbuilder/plugins/default.html
correctiv_chartbuilder-0.0.5.dist-info/DESCRIPTION.rst
correctiv_chartbuilder-0.0.5.dist-info/METADATA
correctiv_chartbuilder-0.0.5.dist-info/metadata.json
correctiv_chartbuilder-0.0.5.dist-info/RECORD
correctiv_chartbuilder-0.0.5.dist-info/top_level.txt
correctiv_chartbuilder-0.0.5.dist-info/WHEEL
