Metadata-Version: 2.0
Name: correctiv-chartbuilder
Version: 0.0.5
Summary: Chartbuilder Django App
Home-page: https://github.org/correctiv/correctiv-chartbuilder/
Author: Stefan Wehrmeyer
Author-email: stefan.wehrmeyer@correctiv.org
License: MIT
Platform: UNKNOWN
Classifier: Development Status :: 5 - Production/Stable
Classifier: Environment :: Web Environment
Classifier: Framework :: Django
Classifier: Intended Audience :: Developers
Classifier: License :: OSI Approved :: MIT License
Classifier: Natural Language :: English
Classifier: Operating System :: OS Independent
Classifier: Programming Language :: Python :: 2.7
Classifier: Topic :: Internet :: WWW/HTTP
Requires-Dist: Django (<1.8)
Requires-Dist: jsonfield
Requires-Dist: djangorestframework
